egoist/__init__.py
egoist/__main__.py
egoist/app.py
egoist/cli.py
egoist/directives.py
egoist/langhelpers.py
egoist/py.typed
egoist/runtime.py
egoist/scan.py
egoist/types.py
egoist/typing.py
egoist/commands/__init__.py
egoist/commands/describe.py
egoist/commands/generate.py
egoist/commands/scan.py
egoist/components/__init__.py
egoist/components/fs.py
egoist/components/fs_tracked_.py
egoist/components/tracker.py
egoist/data/clikit_definitions.py.tmpl
egoist/data/structkit_definitions.py.tmpl
egoist/data/clikit/definitions.py.tmpl
egoist/data/dirkit/definitions.py.tmpl
egoist/data/dirkit/input/hello.tmpl.tmpl
egoist/data/filekit/definitions.py.tmpl
egoist/data/new-command/{definitions}.py.tmpl
egoist/data/new-command/commands/__init__.py
egoist/data/new-command/commands/{name}.py.tmpl
egoist/data/new-directive/{definitions}.py.tmpl
egoist/data/new-directive/directives/__init__.py
egoist/data/new-directive/directives/{name}.py.tmpl
egoist/data/structkit/definitions.py.tmpl
egoist/generators/__init__.py
egoist/generators/clikit/__init__.py
egoist/generators/clikit/runtime.py
egoist/generators/dirkit/__init__.py
egoist/generators/dirkit/runtime.py
egoist/generators/filekit/__init__.py
egoist/generators/filekit/runtime.py
egoist/generators/structkit/__init__.py
egoist/generators/structkit/_context.py
egoist/generators/structkit/_emit.py
egoist/generators/structkit/_walk.py
egoist/generators/structkit/runtime.py
egoist/go/__init__.py
egoist/go/di.py
egoist/go/metadata.py
egoist/go/resolver.py
egoist/go/types.py
egoist/go/walker.py
egoist/internal/__init__.py
egoist/internal/_fnspec.py
egoist/internal/logutil.py
egoist/internal/prestringutil.py
egoist/internal/graph/__init__.py
egoist/internal/graph/draw.py
egoist-0.0.4.dist-info/METADATA
egoist-0.0.4.dist-info/WHEEL
egoist-0.0.4.dist-info/entry_points.txt
egoist-0.0.4.dist-info/top_level.txt
egoist-0.0.4.dist-info/RECORD
