Metadata-Version: 2.1
Name: egoist
Version: 0.0.4
Summary: -
Home-page: https://github.com/podhmo/egoist
Author: podhmo
Author-email: ababjam61+github@gmail.com
License: UNKNOWN
Platform: UNKNOWN
Classifier: Programming Language :: Python :: 3
Classifier: Development Status :: 3 - Alpha
Requires-Python: >=3.7
Requires-Dist: miniconfig (>=0.6.0)
Requires-Dist: metashape (>=0.0.2)
Requires-Dist: prestring (>=0.9.0)
Provides-Extra: dev
Requires-Dist: pytest ; extra == 'dev'
Requires-Dist: pytest-cov ; extra == 'dev'
Requires-Dist: black ; extra == 'dev'
Requires-Dist: flake8 ; extra == 'dev'
Requires-Dist: mypy ; extra == 'dev'
Provides-Extra: testing
Requires-Dist: pytest ; extra == 'testing'
Requires-Dist: pytest-cov ; extra == 'testing'
